{
  "downloadTab": {
    "cart_tab": "Selection",
    "downloads_tab": "Downloads",
    "cart_tab_arialabel": "Selection",
    "downloads_tab_arialabel": "Downloads",
    "download_cart_panel_arialabel": "Download selection panel",
    "download_status_panel_arialabel": "Download status panel",
    "last_updated_time_arialabel": "Last updated time",
    "refresh_download_status_arialabel": "Refresh download status table",
    "last_checked": "Last checked",
    "refreshing_downloads": "Refreshing downloads..."
  },
  "downloadStatus": {
    "id": "ID",
    "filename": "Download Name",
    "fullname": "Full Name",
    "username": "Username",
    "preparedId": "Prepared ID",
    "transport": "Access Method",
    "status": "Availability",
    "size": "Size",
    "createdAt": "Requested Date",
    "deleted": "Deleted",
    "non_https_download_disabled_tooltip": "Instant download not supported for {{transport}} download type",
    "https_download_disabled_tooltip": "This download is not available yet",
    "delete": "Delete {{filename}}",
    "download": "Download {{filename}}",
    "pause": "Pause {{filename}}",
    "remove": "Remove {{filename}} from downloads",
    "resume": "Resume {{filename}}",
    "restore": "Restore {{filename}}",
    "complete": "Available",
    "expired": "Expired",
    "paused": "Paused",
    "preparing": "Preparing",
    "restoring": "Restoring from tape",
    "queued": "Queued",
    "progress": "Progress",
    "calculating_progress": "Calculating...",
    "progress_unavailable": "Unknown",
    "progress_complete": "",
    "progress_queued": "Queued"
  },
  "downloadConfirmDialog": {
    "close_arialabel": "Close download confirmation dialog",
    "dialog_arialabel": "Download confirmation dialog",
    "email_label": "Email Address (optional)",
    "email_help": "Send me download status messages via email.",
    "email_error": "Please ensure the email you have entered is valid.",
    "access_methods_error": "Download access method statuses unable to be fetched. Please try again later.",
    "access_method_error": "The status of access method {{method}} is unable to be fetched. If required, use an alternative method.",
    "day_one": "day",
    "day_other": "days",
    "hour_one": "hour",
    "hour_other": "hours",
    "minute_one": "minute",
    "minute_other": "minutes",
    "second_one": "second",
    "second_other": "seconds",
    "loading_confirmation": "Loading Confirmation...",
    "dialog_title": "Confirm Your Download",
    "download_name_label": "Download Name (optional)",
    "download_name_helpertext": "Enter a custom file name or leave as the default format ($t(downloadConfirmDialog.download_name_default_format)).",
    "download_name_default_format": "facilityName_yyyy-MM-dd_HH-mm-ss",
    "access_method_label": "Access method",
    "access_method_helpertext": "Select an access method for download.",
    "access_method_helpertext_all_disabled_error": "Access methods currently unavailable.",
    "access_method_helpertext_disabled_error": "This access method is currently disabled.",
    "access_method_info": "Access Method Information",
    "download_size": "Download Size",
    "estimated_download_times": "Estimated download times",
    "download": "Download",
    "download_success": "Successfully submitted download request",
    "download_error": "<0>Your download request was unsuccessful</0><1/>(No download information was received)",
    "confirmation_download_name": "Download Name",
    "confirmation_access_method": "Access Method",
    "confirmation_email": "Email Address",
    "view_my_downloads": "View My Downloads",
    "submitting_cart": "Preparing..."
  },
  "downloadCart": {
    "name": "Name",
    "type": "Type",
    "size": "Size",
    "fileCount": "File Count",
    "calculating": "Calculating",
    "remove": "Remove {{name}} from selection",
    "remove_all": "Remove All",
    "download": "Download Selection",
    "generate_DOI": "Generate DOI",
    "mintability_loading": "Checking whether you have permission to mint these files...",
    "not_mintable": "You do not have permission to mint these files",
    "number_of_files": "Number of files",
    "total_size": "Total size",
    "no_selections": "No data selected. <2>Browse</2> or <6>search</6> for data.",
    "browse_link": "/browse/investigation",
    "search_link": "/search/data",
    "empty_items_error": "You have selected some empty items - please remove them to proceed with downloading your selection",
    "file_limit_error": "Too many files - you have exceeded limit of {{fileCountMax}} files - please remove some files",
    "size_limit_error": "Too much data - you have exceeded limit of {{totalSizeMax}} - please remove some files"
  },
  "acceptDataPolicy": {
    "accept": "Accept",
    "data_policy": "Accept data policy: Lorem ipsum dolor sit amet, consectetur adipiscing elit, sed do eiusmod tempor incididunt ut labore et dolore magna aliqua. Ut enim ad minim veniam, quis nostrud exercitation ullamco laboris nisi ut aliquip ex ea commodo consequat. Duis aute irure dolor in reprehenderit in voluptate velit esse cillum lore eu fugiat nulla pariatur. Excepteur sint occaecat cupidatat non proident, sunt in culpa qui officia deserunt mollit anim id est laborum."
  },
  "DOIGenerationForm": {
    "page_header": "Generate DOI",
    "data_header": "Data",
    "form_header": "Details",
    "title": "DOI Title",
    "description": "DOI Description",
    "creators": "Creators & Contributors",
    "username": "Username",
    "add_creator": "Add Creator",
    "add_contributor": "Add Contributor",
    "creator_name": "Name",
    "creator_affiliation": "Affiliation",
    "creator_email": "Email",
    "creator_type": "Contributor Type",
    "creator_action": "Action",
    "delete_creator": "Delete",
    "related_dois": "Related DOIs",
    "related_doi": "DOI",
    "add_related_doi": "Add DOI",
    "related_doi_doi": "DOI",
    "related_doi_relationship": "Relationship",
    "related_doi_resource_type": "Resource Type",
    "related_doi_action": "Action",
    "delete_related_doi": "Delete",
    "generate_DOI": "Generate DOI",
    "cart_tabs_aria_label": "cart tabs",
    "cart_tab_investigations": "Investigations",
    "cart_tab_datasets": "Datasets",
    "cart_tab_datafiles": "Datafiles",
    "cart_table_name": "Name"
  },
  "DOIConfirmDialog": {
    "dialog_title": "Mint Confirmation",
    "mint_success": "Mint was successful",
    "mint_error": "Mint was unsuccessful",
    "mint_loading": "Loading...",
    "concept_doi_label": "Concept DOI",
    "version_doi_label": "Version DOI",
    "error_label": "Error",
    "view_data_publication": "View Data Publication"
  }
}
