{
  "facilityName": "Generic",
  "idsUrl": "https://scigateway-preprod.esc.rl.ac.uk:8181/ids",
  "apiUrl": "http://scigateway-preprod.esc.rl.ac.uk:5000",
  "downloadApiUrl": "https://scigateway-preprod.esc.rl.ac.uk:8181/topcat",
  "helpSteps": [
    {
      "target": "#plugin-link--search-data",
      "content":
        "DataGateway Search allows you to search for specific datasets, datafiles or investigations using date and text filters"
    },
    {
      "target": ".tour-search-tab-select",
      "content": "Select which type of data to view the search results for"
    }
  ],
  "routes": [
    {
      "section": "Test",
      "link": "/search/data",
      "displayName": "Search",
      "order": 0
    }
  ]
}
